iglib/__init__.py
iglib/flowerscript.py
iglib/igarchive.py
iglib-1.0.0.dist-info/METADATA
iglib-1.0.0.dist-info/WHEEL
iglib-1.0.0.dist-info/top_level.txt
iglib-1.0.0.dist-info/RECORD
